PIP_PACKAGE_TEST
