Metadata-Version: 1.0
Name: Berrys-test-package
Version: 0.1.1
Summary: lets figure this out
Home-page: UNKNOWN
Author: Berry Adams
Author-email: UNKNOWN
License: NA
Platform: UNKNOWN
